estimationtools/__init__.py
estimationtools/burndownchart.py
estimationtools/hoursinplaceeditor.py
estimationtools/hoursremaining.py
estimationtools/utils.py
estimationtools/workloadchart.py
estimationtools/htdocs/jquery.jeditable.js
estimationtools/htdocs/jquery.jeditable.mini.js
estimationtools/templates/edithours.html
TracEstimationTools-0.5.0.dist-info/METADATA
TracEstimationTools-0.5.0.dist-info/WHEEL
TracEstimationTools-0.5.0.dist-info/entry_points.txt
TracEstimationTools-0.5.0.dist-info/top_level.txt
TracEstimationTools-0.5.0.dist-info/RECORD
